tsp_wrapper/brokers/__init__.py
tsp_wrapper/brokers/broker.py
tsp_wrapper/brokers/builder.py
tsp_wrapper/brokers/consumer.py
tsp_wrapper/brokers/producer.py
tsp_wrapper/config/__init__.py
tsp_wrapper/config/logging.conf
tsp_wrapper/config/settings.py
tsp_wrapper/middleware/__init__.py
tsp_wrapper/middleware/schema.py
tsp_wrapper/services.py
tsp_wrapper/tsp.py
tsp_wrapper-0.1.0.dist-info/LICENSE
tsp_wrapper-0.1.0.dist-info/METADATA
tsp_wrapper-0.1.0.dist-info/WHEEL
tsp_wrapper-0.1.0.dist-info/RECORD
