Metadata-Version: 2.1
Name: tsp-wrapper
Version: 0.1.0
Summary: 
Author: amirbahador
Author-email: amirbahador.pv@gmail.com
Requires-Python: ==3.10.9
Classifier: Programming Language :: Python :: 3
Requires-Dist: kombu (>=5.2.4,<6.0.0)
Requires-Dist: ortools (==9.6.2534)
Requires-Dist: python-decouple (>=3.8,<4.0)
Requires-Dist: python-json-logger (>=2.0.7,<3.0.0)
Requires-Dist: scipy (==1.10.1)
Requires-Dist: typer (>=0.7.0,<0.8.0)
